<?xml version="1.0" encoding="utf-8"?>
<Entity parent="template_unit_cavalry_ranged_javelineer">
  <Identity>
    <Civ>maur</Civ>
    <Classes datatype="tokens">Indian</Classes>
    <Icon>units/maur_cavalry_javelinist_b.png</Icon>
    <RequiredTechnology>phase_village</RequiredTechnology>
    <SelectionGroupName>units/maur/cavalry_javelineer</SelectionGroupName>
    <SpecificName>Indian Light Cavalry</SpecificName>
  </Identity>
  <VisualActor>
    <Actor>units/mauryans/cavalry_javelinist_b_m.xml</Actor>
  </VisualActor>
</Entity>
