{
  "affects": ["NorthAfricanElephant"],
  "autoResearch": true,
  "description": "The Carthaginians, Kushites, and Ptolemies used North African elephants, which were smaller and weaker than the more expensive Indian elephants.",
  "genericName": "North African Elephants",
  "modifications": [
    {"value": "Attack/Melee/Crush",    "multiply": 0.9},
    {"value": "Attack/Melee/Hack",     "multiply": 0.9},
    {"value": "Attack/Melee/Pierce",   "multiply": 0.9},
    {"value": "Attack/Melee/Thrust",   "multiply": 0.9},
    {"value": "Cost/BuildTime",        "multiply": 0.9},
    {"value": "Cost/Resources/food",   "multiply": 0.9},
    {"value": "Cost/Resources/silver", "multiply": 0.9},
    {"value": "Health/Max",            "multiply": 0.9}
  ],
  "tooltip": "War Elephants −10% food and silver costs, training time, health, and melee attack damage."
}
