<?xml version="1.0" encoding="utf-8"?>
<Entity parent="template_structure_civic_theatre">
  <Footprint replace="">
    <Circle radius="25"/>
    <Height>10</Height>
  </Footprint>
  <Health>
    <SpawnEntityOnDeath>decay|rubble/rubble_stone_6x6</SpawnEntityOnDeath>
  </Health>
  <Identity>
    <Civ>sele</Civ>
    <SpecificName>Θέατρον</SpecificName>
  </Identity>
  <Obstruction>
    <Static width="40" depth="46"/>
  </Obstruction>
  <VisualActor>
    <Actor>structures/spartans/theatron.xml</Actor>
    <FoundationActor>structures/fndn_theatron.xml</FoundationActor>
  </VisualActor>
</Entity>
